vector_db_query/__init__.py
vector_db_query/__main__.py
vector_db_query/multi_dim_query.py
vector_db_query/py.typed
vector_db_query/query_system.py
vector_db_query/universal_reader.py
vector_db_query/api/__init__.py
vector_db_query/api/app.py
vector_db_query/api/webhooks/__init__.py
vector_db_query/api/webhooks/fireflies.py
vector_db_query/cli/__init__.py
vector_db_query/cli/main.py
vector_db_query/cli/commands/__init__.py
vector_db_query/cli/commands/api.py
vector_db_query/cli/commands/auth.py
vector_db_query/cli/commands/config.py
vector_db_query/cli/commands/datasources.py
vector_db_query/cli/commands/dedup.py
vector_db_query/cli/commands/fireflies.py
vector_db_query/cli/commands/formats.py
vector_db_query/cli/commands/googledrive.py
vector_db_query/cli/commands/interactive.py
vector_db_query/cli/commands/logging.py
vector_db_query/cli/commands/mcp.py
vector_db_query/cli/commands/mcp_enhanced.py
vector_db_query/cli/commands/migrate.py
vector_db_query/cli/commands/monitor.py
vector_db_query/cli/commands/performance.py
vector_db_query/cli/commands/process.py
vector_db_query/cli/commands/process_enhanced.py
vector_db_query/cli/commands/process_fixed.py
vector_db_query/cli/commands/quickstart.py
vector_db_query/cli/commands/read.py
vector_db_query/cli/commands/setup.py
vector_db_query/cli/commands/vector.py
vector_db_query/cli/interactive/__init__.py
vector_db_query/cli/interactive/animations.py
vector_db_query/cli/interactive/app.py
vector_db_query/cli/interactive/base.py
vector_db_query/cli/interactive/config.py
vector_db_query/cli/interactive/config_ui.py
vector_db_query/cli/interactive/demo.py
vector_db_query/cli/interactive/demo_app.py
vector_db_query/cli/interactive/demo_config_ui.py
vector_db_query/cli/interactive/demo_file_browser.py
vector_db_query/cli/interactive/demo_keyboard.py
vector_db_query/cli/interactive/demo_polish.py
vector_db_query/cli/interactive/demo_preferences.py
vector_db_query/cli/interactive/demo_progress.py
vector_db_query-1.0.0.dist-info/licenses/LICENSE
vector_db_query-1.0.0.dist-info/METADATA
vector_db_query-1.0.0.dist-info/WHEEL
vector_db_query-1.0.0.dist-info/entry_points.txt
vector_db_query-1.0.0.dist-info/top_level.txt
vector_db_query-1.0.0.dist-info/RECORD
