Metadata-Version: 2.4
Name: vector-db-query
Version: 1.0.0
Summary: CLI application for vector database queries using LLMs via MCP
Home-page: https://github.com/your-org/vector-db-query
Author: Vector DB Query Team
Author-email: Vector DB Query Team <team@example.com>
License: MIT
Project-URL: Homepage, https://github.com/yourusername/vector-db-query
Project-URL: Documentation, https://vector-db-query.readthedocs.io
Project-URL: Repository, https://github.com/yourusername/vector-db-query
Project-URL: Issues, https://github.com/yourusername/vector-db-query/issues
Project-URL: Changelog, https://github.com/yourusername/vector-db-query/blob/main/CHANGELOG.md
Keywords: vector-database,llm,mcp,embeddings,qdrant
Classifier: Development Status :: 4 - Beta
Classifier: Intended Audience :: Developers
Classifier: License :: OSI Approved :: MIT License
Classifier: Programming Language :: Python :: 3
Classifier: Programming Language :: Python :: 3.9
Classifier: Programming Language :: Python :: 3.10
Classifier: Programming Language :: Python :: 3.11
Classifier: Topic :: Software Development :: Libraries :: Python Modules
Classifier: Topic :: Scientific/Engineering :: Artificial Intelligence
Requires-Python: >=3.9
License-File: LICENSE
Requires-Dist: google-generativeai>=0.8.0
Requires-Dist: qdrant-client>=1.7.0
Requires-Dist: mcp>=1.0.0
Requires-Dist: click>=8.1.0
Requires-Dist: pyyaml>=6.0
Requires-Dist: python-dotenv>=1.0.0
Requires-Dist: numpy>=1.24.0
Requires-Dist: docker>=7.0.0
Requires-Dist: requests>=2.32.4
Requires-Dist: rich>=13.7.0
Requires-Dist: questionary>=2.0.1
Requires-Dist: pydantic>=2.5.0
Requires-Dist: pydantic-settings>=2.0.0
Requires-Dist: aiofiles>=23.2.0
Requires-Dist: httpx>=0.25.0
Requires-Dist: aiohttp>=3.12.14
Requires-Dist: urllib3>=2.5.0
Requires-Dist: tqdm>=4.66.3
Requires-Dist: cryptography>=44.0.1
Requires-Dist: jinja2>=3.1.6
Requires-Dist: pyjwt>=2.8.0
Requires-Dist: pypdf2>=3.0.0
Requires-Dist: python-docx>=1.1.0
Requires-Dist: chardet>=5.2.0
Requires-Dist: python-json-logger>=2.0.0
Requires-Dist: openai>=1.0.0
Requires-Dist: cohere>=5.0.0
Requires-Dist: openpyxl>=3.1.0
Requires-Dist: xlrd>=2.0.0
Requires-Dist: pandas>=2.0.0
Requires-Dist: python-pptx>=0.6.0
Requires-Dist: beautifulsoup4>=4.12.0
Requires-Dist: lxml>=4.9.0
Requires-Dist: html2text>=2020.1.16
Requires-Dist: pillow>=10.0.0
Requires-Dist: pytesseract>=0.3.0
Requires-Dist: pdf2image>=1.16.0
Provides-Extra: dev
Requires-Dist: pytest>=7.4.0; extra == "dev"
Requires-Dist: black>=24.3.0; extra == "dev"
Requires-Dist: ruff>=0.1.0; extra == "dev"
Requires-Dist: mypy>=1.5.0; extra == "dev"
Requires-Dist: pre-commit>=3.4.0; extra == "dev"
Provides-Extra: docs
Requires-Dist: sphinx>=7.0.0; extra == "docs"
Requires-Dist: sphinx-rtd-theme>=2.0.0; extra == "docs"
Requires-Dist: sphinx-autodoc-typehints>=1.24.0; extra == "docs"
Requires-Dist: sphinx-copybutton>=0.5.2; extra == "docs"
Requires-Dist: myst-parser>=2.0.0; extra == "docs"
Requires-Dist: sphinxcontrib-mermaid>=0.9.2; extra == "docs"
Provides-Extra: monitoring
Requires-Dist: streamlit>=1.29.0; extra == "monitoring"
Requires-Dist: plotly>=5.18.0; extra == "monitoring"
Requires-Dist: psutil>=5.9.0; extra == "monitoring"
Requires-Dist: watchdog>=3.0.0; extra == "monitoring"
Requires-Dist: starlette>=0.47.2; extra == "monitoring"
Requires-Dist: transformers>=4.52.1; extra == "monitoring"
Dynamic: license-file
